{"dissolution_date": null, "name_uppercase": "ABDUL RAHIM BIN PANDAK KAMARUDIN", "end_date": null, "image": null, "contractors": [{"status": "Aktif", "fax": "03-74920022", "sum_projects_value": 57655552, "rob": "", "roc": "73400D", "telephone": "03-74920011", "director_name": "ABDUL RAHIM BIN PANDAK KAMARUDIN", "postcode": "47301", "company": "HAZEN TRADING WATER TREATMENT SDN. BHD.", "address": "LOT 503, BLOCK A KELANA BUSINESS CENTRE ", "cidb_pengkhususan": "CE04 - EMPANGAN,CE19 - SISTEM PEMBETUNGAN,CE21 - KERJA-KERJA AM KEJURUTERAAN AWAM,M14 - SISTEM KAWALAN PENCEMARAN,M15 - KELENGKAPAN MEKANIKAL PELBAGAI", "pkk_kelas": "", "id": 96938, "town": "PETALING JAYA", "pkk_nopendaftaran": "", "ctime": "2012-04-30 21:53:49", "cidb_vgred": "G7", "cidb_nopendaftaran": "1960606-SL001632", "source": "http://202.190.73.10/directory/local_contractor_details.php?cont_id=7252", "location": {"Lat": "3.10415", "postcode": "47301", "Name": "Petaling Jaya", "Long": "101.61284", "id": 41}, "cidb_tarikhluputpendaftaran": "2012-12-02", "num_projects": 13, "modalberbayar": "1000000", "cont_id": "7252", "cidb_bumiputera": "", "email": "", "tradinglicense": "", "modaldibenarkan": ""}, {"status": "Aktif", "fax": "03-21487654", "sum_projects_value": 37975638, "rob": "", "roc": "119752T", "telephone": "03-21488913/6963", "director_name": "ABDUL RAHIM BIN PANDAK KAMARUDIN", "postcode": "47301", "company": "TEAM CONTRACT SDN. BHD.", "address": "LOT 503, BLOCK A KELANA BUSINESS CENTRE JALAN SS 7/2", "cidb_pengkhususan": "B04 - KERJA AM BANGUNAN,CE04 - EMPANGAN,CE19 - SISTEM PEMBETUNGAN,CE21 - KERJA-KERJA AM KEJURUTERAAN AWAM,M15 - KELENGKAPAN MEKANIKAL PELBAGAI", "pkk_kelas": "", "id": 121668, "town": "PETALING JAYA", "pkk_nopendaftaran": "", "ctime": "2012-04-30 20:46:36", "cidb_vgred": "G5", "cidb_nopendaftaran": "1960313-SL000624", "source": "http://202.190.73.10/directory/local_contractor_details.php?cont_id=32112", "location": {"Lat": "3.10415", "postcode": "47301", "Name": "Petaling Jaya", "Long": "101.61284", "id": 41}, "cidb_tarikhluputpendaftaran": "2011-04-20", "num_projects": 8, "modalberbayar": "400002", "cont_id": "32112", "cidb_bumiputera": "", "email": "", "tradinglicense": "", "modaldibenarkan": ""}], "html_url": "http://sinar-malaysia.popit.mysociety.org/persons/545e46545222837c2c059169", "organization_id": null, "person_id": "545e46545222837c2c059169", "organization": null, "summary": null, "id": 2483, "projects": [{"tarikh_anugerah": "1996-08-15", "nilai": "1375000", "tajuk": "Prop. Cons. & Completion & Maintenance Of Proprietry ' Oxidation Ditch' Sewerage Treatment\nPlant C, Selangor.", "company": "HAZEN TRADING WATER TREATMENT SDN. BHD.", "cont_id": "7252", "id": 94145, "director_name": "ABDUL RAHIM BIN PANDAK KAMARUDIN"}, {"tarikh_anugerah": "1996-11-14", "nilai": "813000", "tajuk": "Dis. Erec. Const. To relevent Authority A Swage Tretment Plant Of Extended Aeration System Phase 2B, Johor", "company": "HAZEN TRADING WATER TREATMENT SDN. BHD.", "cont_id": "7252", "id": 94146, "director_name": "ABDUL RAHIM BIN PANDAK KAMARUDIN"}, {"tarikh_anugerah": "1996-12-11", "nilai": "1564300", "tajuk": "Sewerage Treatment Plant For Phase 4, Cad. Arab Malaysian Ind. Park, Di Atas Lot 3715, Mk. Setul, Dae. Seremban, N.S", "company": "HAZEN TRADING WATER TREATMENT SDN. BHD.", "cont_id": "7252", "id": 94147, "director_name": "ABDUL RAHIM BIN PANDAK KAMARUDIN"}, {"tarikh_anugerah": "1997-01-13", "nilai": "6618889", "tajuk": "Supply, Install,Test & Commiss.- Sewage Treatment Plant Package 'C', Lot 20,21,30,49,50,51 &\n52 UEP Subang Jaya II, Sel.", "company": "HAZEN TRADING WATER TREATMENT SDN. BHD.", "cont_id": "7252", "id": 94148, "director_name": "ABDUL RAHIM BIN PANDAK KAMARUDIN"}, {"tarikh_anugerah": "1997-07-22", "nilai": "5252835", "tajuk": "Proposed Design, Built & Comm. Of Sewerage Treatment Plant No. 2, Bandar  Kinrara, Selangor", "company": "HAZEN TRADING WATER TREATMENT SDN. BHD.", "cont_id": "7252", "id": 94149, "director_name": "ABDUL RAHIM BIN PANDAK KAMARUDIN"}, {"tarikh_anugerah": "1997-07-29", "nilai": "2600000", "tajuk": "Sewage Treatment Plant- Lot 14843-14844,15929-15930, 16627-16229, 16332-17589 & 17592-\n17816, Mk. Rantau, Seremban", "company": "HAZEN TRADING WATER TREATMENT SDN. BHD.", "cont_id": "7252", "id": 94150, "director_name": "ABDUL RAHIM BIN PANDAK KAMARUDIN"}, {"tarikh_anugerah": "1997-12-03", "nilai": "5673300", "tajuk": "Design, Const. Supply, Inst. Test., Comm. Handing Over & Maintenance Of The Sewage Treatment & Anc. Works (Module 1)", "company": "HAZEN TRADING WATER TREATMENT SDN. BHD.", "cont_id": "7252", "id": 94151, "director_name": "ABDUL RAHIM BIN PANDAK KAMARUDIN"}, {"tarikh_anugerah": "1998-06-03", "nilai": "8445290", "tajuk": "Design, Obtain.  Approval, Const. Comp & M'tenance Of Prop. Sewage T/ment Plant (STP) & Assoc. Wks,  Putra Perdana Dev.", "company": "HAZEN TRADING WATER TREATMENT SDN. BHD.", "cont_id": "7252", "id": 94152, "director_name": "ABDUL RAHIM BIN PANDAK KAMARUDIN"}, {"tarikh_anugerah": "1999-04-28", "nilai": "3013120", "tajuk": "Sewerage Treatment Plant For Cad. Pembangunan Di Lot 3 & 60, Di Sbhg Ladang Sg. Kapar, Mk. Kapar, Dae. Klang, Selangor", "company": "HAZEN TRADING WATER TREATMENT SDN. BHD.", "cont_id": "7252", "id": 94153, "director_name": "ABDUL RAHIM BIN PANDAK KAMARUDIN"}, {"tarikh_anugerah": "2000-10-24", "nilai": "3663667", "tajuk": "Proposed Sewerage Treatment Plant (STP) And Associated  Works For Putera Perdana Development (Phase 2)", "company": "HAZEN TRADING WATER TREATMENT SDN. BHD.", "cont_id": "7252", "id": 94154, "director_name": "ABDUL RAHIM BIN PANDAK KAMARUDIN"}, {"tarikh_anugerah": "2001-04-17", "nilai": "7500000", "tajuk": "Pembangunan Sg. Kapar Indah - Design, Suplly, Construct, Testing and Commissioning Of Sewerage Treatment Plant For Phase 2, 3 & 4 Contract Wk", "company": "HAZEN TRADING WATER TREATMENT SDN. BHD.", "cont_id": "7252", "id": 94155, "director_name": "ABDUL RAHIM BIN PANDAK KAMARUDIN"}, {"tarikh_anugerah": "2002-07-11", "nilai": "1741323", "tajuk": "Construction, Completion, Testing, Commissioning & Maintenance Of Sewage Lifting Station No.4, Pumping Main Gravity Sewers & Appurtenances, Putra Heights", "company": "HAZEN TRADING WATER TREATMENT SDN. BHD.", "cont_id": "7252", "id": 94156, "director_name": "ABDUL RAHIM BIN PANDAK KAMARUDIN"}, {"tarikh_anugerah": "2002-08-02", "nilai": "9394828", "tajuk": "Construction, Delivery, Fabrication, Installation, Testing, Commissioning & Maintenance Of The Sewage Treatment Plant", "company": "HAZEN TRADING WATER TREATMENT SDN. BHD.", "cont_id": "7252", "id": 94157, "director_name": "ABDUL RAHIM BIN PANDAK KAMARUDIN"}, {"tarikh_anugerah": "1998-05-28", "nilai": "5537659", "tajuk": "Cadangan Membina & Menyelenggara Sistem Pam Kumbahan Dan Kerja Berkaitan Di Seksyen 4 & 13, Pusat Bdr. Sg. Buloh", "company": "TEAM CONTRACT SDN. BHD.", "cont_id": "32112", "id": 299969, "director_name": "ABDUL RAHIM BIN PANDAK KAMARUDIN"}, {"tarikh_anugerah": "2001-04-12", "nilai": "7455120", "tajuk": "Design, Const., Complete, Operate & Maintain Sludge Treatment Plant & An Intermediate Pumping Station Including All Ancillary Works (PT2A1-6) for Kota Seriemas,", "company": "TEAM CONTRACT SDN. BHD.", "cont_id": "32112", "id": 299970, "director_name": "ABDUL RAHIM BIN PANDAK KAMARUDIN"}, {"tarikh_anugerah": "2003-09-22", "nilai": "12788000", "tajuk": "Merekabentuk Mendapatkan Kelulusan, Membina, Menyiapkan & Menyelenggara Loji Rawatan Kumbahan", "company": "TEAM CONTRACT SDN. BHD.", "cont_id": "32112", "id": 299971, "director_name": "ABDUL RAHIM BIN PANDAK KAMARUDIN"}, {"tarikh_anugerah": "2003-12-10", "nilai": "1530000", "tajuk": "Merekabentuk, Mendptkn Kelulusan, Membina & Menyiapkan Cdg Pembgn & Penempatan Perumahan Setinggan Di Tanah Rezab KTMB Fasa 2 Utk Menyelenggara Loji Rawatan Kumbahan (Modul 2)", "company": "TEAM CONTRACT SDN. BHD.", "cont_id": "32112", "id": 299972, "director_name": "ABDUL RAHIM BIN PANDAK KAMARUDIN"}, {"tarikh_anugerah": "2003-12-12", "nilai": "505309", "tajuk": "Upgrading Pumping Station At Section 13 Kota Damansara", "company": "TEAM CONTRACT SDN. BHD.", "cont_id": "32112", "id": 299973, "director_name": "ABDUL RAHIM BIN PANDAK KAMARUDIN"}, {"tarikh_anugerah": "2004-01-05", "nilai": "3950000", "tajuk": "Supply,Delivery,Installation,Testing And Commissioning Of Air Conditioning Services And Ventilation Services On Lot 108,Block 18 And Lot 85,Block 17,Mukah Land District And State Land Mukah", "company": "TEAM CONTRACT SDN. BHD.", "cont_id": "32112", "id": 299974, "director_name": "ABDUL RAHIM BIN PANDAK KAMARUDIN"}, {"tarikh_anugerah": "2004-08-14", "nilai": "5455800", "tajuk": "Cdg Merekabentuk, Mendptkn Kelulusan Membina, Menyiapkan & Menyelenggara Loji Rawatan Kumbahan Berkapasiti 57,000 Pe & Kerja-kerja Berkaitan Di Laman 1 Bernam Jaya", "company": "TEAM CONTRACT SDN. BHD.", "cont_id": "32112", "id": 299975, "director_name": "ABDUL RAHIM BIN PANDAK KAMARUDIN"}, {"tarikh_anugerah": "2006-11-14", "nilai": "753750", "tajuk": "Cdg Merekabentuk,Membina & Menyiapkan 46U R/Banglo Setingkat (50' X 80') 60U R/Berkembar Setingkat Lot(40' X 80') Serta Sebuah Pencawng Elektrik Loji Kumbahan & Menara Tangki Air Di Plot 3 (Sewerage Treatment Plant - Spa)", "company": "TEAM CONTRACT SDN. BHD.", "cont_id": "32112", "id": 299976, "director_name": "ABDUL RAHIM BIN PANDAK KAMARUDIN"}], "founding_date": null, "name": "Abdul Rahim Bin Pandak Kamarudin", "url": "http://sinar-malaysia.popit.mysociety.org/api/v0.1/persons/545e46545222837c2c059169", "gender": null, "slug": "abdul-rahim-bin-pandak-kamarudin", "death_date": null, "proxy_image": null, "start_date": null, "memberships": [{"area_id": null, "end_date": "", "url": "http://sinar-malaysia.popit.mysociety.org/api/v0.1/memberships/5570788145c48d597e976cf6", "area_name": null, "html_url": "http://sinar-malaysia.popit.mysociety.org/memberships/5570788145c48d597e976cf6", "id": 2484, "label": null, "organization_id": "53633b5a19ee29270d8a9ecf", "post_id": null, "membership_id": "5570788145c48d597e976cf6", "role": "Member of Parliament", "person_id": 2483, "director_name": "Abdul Rahim Bin Pandak Kamarudin", "start_date": "2013"}], "birth_date": null, "num_projects": 21, "email": null, "initials": null}