{"dissolution_date": null, "name_uppercase": "ZAKARIA BIN ABDUL HAMID", "end_date": null, "image": null, "contractors": [{"status": "Aktif", "fax": "03-33424327/9816", "sum_projects_value": 4035530548, "rob": "", "roc": "12737K", "telephone": "03-33424323", "director_name": "ZAKARIA BIN ABDUL HAMID", "postcode": "41300", "company": "MUHIBBAH ENGINEERING (M) BHD.", "address": "LOT 579 & 586, 2ND MILE JALAN BATU TIGA LAMA ", "cidb_pengkhususan": "B02 - IBS : SISTEM KERANGKA KELULI,B04 - KERJA AM BANGUNAN,B05 - KERJA CERUCUK,CE01 - PEMBINAAN JALAN DAN PAVMEN,CE02 - PEMBINAAN JAMBATAN,CE03 - STRUKTUR MERIN,CE04 - EMPANGAN,CE06 - SISTEM KAWALAN PENGAIRAN DAN BANJIR,CE07 - TREK KERETAPI,CE08 - SISTEM PERLINDUNGAN CERUN,CE10 - KERJA CERUCUK,CE13 - PEMASANGAN TANDA,CE15 - KERJA-KERJA PEMBINAAN LUAR PERSISIR,CE16 - KERJA PEMBINAAN DAN PENYELENGGARAAN DI BAWAH AIR,CE17 - LAPANGAN TERBANG,CE19 - SISTEM PEMBETUNGAN,CE21 - KERJA-KERJA AM KEJURUTERAAN AWAM,CE24 - STRUKTUR KEJURUTERAAN AWAM,E11 - KERJA-KERJA AM ELEKTRIK,M15 - KELENGKAPAN MEKANIKAL PELBAGAI", "pkk_kelas": "", "id": 51010, "town": "KLANG", "pkk_nopendaftaran": "", "ctime": "2012-04-30 20:11:32", "cidb_vgred": "G7", "cidb_nopendaftaran": "1960202-SL000263", "source": "http://202.190.73.10/directory/local_contractor_details.php?cont_id=32050", "location": {"Lat": "3.0641", "postcode": "41300", "Name": "Klang", "Long": "101.466", "id": 454}, "cidb_tarikhluputpendaftaran": "2015-03-13", "num_projects": 63, "modalberbayar": "397713750", "cont_id": "32050", "cidb_bumiputera": "", "email": "admin.qs@muhibbah.com.my", "tradinglicense": "", "modaldibenarkan": ""}, {"status": "Aktif", "fax": "04-6449959", "sum_projects_value": 4289200, "rob": "", "roc": "569633K", "telephone": "04-6464959", "director_name": "ZAKARIA BIN ABDUL HAMID", "postcode": "11950", "company": "CELESTA JAYA SDN. BHD.", "address": "114-B, SECOND FLOOR JALAN MAYANG PASIR BAYAN BARU", "cidb_pengkhususan": "B01 - IBS : SISTEM KONKRIT PASANG SIAP,B02 - IBS : SISTEM KERANGKA KELULI,B04 - KERJA AM BANGUNAN,B05 - KERJA CERUCUK,B07 - KERJA HIASAN DALAMAN,B14 - KERJA-KERJA CAT,B15 - PEMASANGAN BUMBUNG DAN 'CLADDING' LOGAM,CE10 - KERJA CERUCUK,CE21 - KERJA-KERJA AM KEJURUTERAAN AWAM", "pkk_kelas": "", "id": 53698, "town": "BAYAN LEPAS", "pkk_nopendaftaran": "", "ctime": "2012-04-30 20:29:22", "cidb_vgred": "G6", "cidb_nopendaftaran": "0120051004-KD106657", "source": "http://202.190.73.10/directory/local_contractor_details.php?cont_id=119863", "location": {"Lat": "5.32711", "postcode": "11950", "Name": "Bayan Lepas", "Long": "100.28508", "id": 171}, "cidb_tarikhluputpendaftaran": "2012-10-02", "num_projects": 1, "modalberbayar": "505000", "cont_id": "119863", "cidb_bumiputera": "", "email": "", "tradinglicense": "", "modaldibenarkan": ""}], "html_url": "http://sinar-malaysia.popit.mysociety.org/persons/545e483f5222837c2c059623", "organization_id": null, "person_id": "545e483f5222837c2c059623", "organization": null, "summary": null, "id": 3590, "projects": [{"tarikh_anugerah": "2009-07-23", "nilai": "4289200", "tajuk": "Membina Blok Bangunan Pejabat Pelajaran Daerah Baling/Sik", "company": "CELESTA JAYA SDN. BHD.", "cont_id": "119863", "id": 47797, "director_name": "ZAKARIA BIN ABDUL HAMID"}, {"tarikh_anugerah": "1996-08-16", "nilai": "3038000", "tajuk": "Chemical Tank Farm For Chemquest Terminals Sdn Bhd At Westport Pulau Indah - Tank Fabrication", "company": "MUHIBBAH ENGINEERING (M) BHD.", "cont_id": "32050", "id": 180708, "director_name": "ZAKARIA BIN ABDUL HAMID"}, {"tarikh_anugerah": "1996-09-12", "nilai": "2528600", "tajuk": "Chemical Tank Farm For Chemquest Terminals Sdn Bhd At Westport Pulau Indah - Piping Works", "company": "MUHIBBAH ENGINEERING (M) BHD.", "cont_id": "32050", "id": 180709, "director_name": "ZAKARIA BIN ABDUL HAMID"}, {"tarikh_anugerah": "1996-09-17", "nilai": "84531035", "tajuk": "Cad. Tambahan & Ubahsuai Terminal Bldg. & Ancillary Bldg. di L.Terbang Senai, Johor Bahru, Johor.", "company": "MUHIBBAH ENGINEERING (M) BHD.", "cont_id": "32050", "id": 180710, "director_name": "ZAKARIA BIN ABDUL HAMID"}, {"tarikh_anugerah": "1996-12-10", "nilai": "103282459", "tajuk": "The Execution & Completion of Civil & Building Works for Malaysian Airline System Berhad.", "company": "MUHIBBAH ENGINEERING (M) BHD.", "cont_id": "32050", "id": 180711, "director_name": "ZAKARIA BIN ABDUL HAMID"}, {"tarikh_anugerah": "1997-04-02", "nilai": "33330000", "tajuk": "Prop. West Wharf Phase 1, Offshore Jetty, Access Trestles & Conveyor Gantry Supports, Kemaman Port", "company": "MUHIBBAH ENGINEERING (M) BHD.", "cont_id": "32050", "id": 180712, "director_name": "ZAKARIA BIN ABDUL HAMID"}, {"tarikh_anugerah": "1997-04-04", "nilai": "28031554", "tajuk": "Breakwater,ShoreProtection,Seawall,Revetment,Land Reclamation & Dreading Work for waterway P.Dickson Inter.Marina (P)", "company": "MUHIBBAH ENGINEERING (M) BHD.", "cont_id": "32050", "id": 180713, "director_name": "ZAKARIA BIN ABDUL HAMID"}, {"tarikh_anugerah": "1997-04-04", "nilai": "32554725", "tajuk": "Prop. Liquid Bulk Terminal on Lot 55710, West Port, Selangor", "company": "MUHIBBAH ENGINEERING (M) BHD.", "cont_id": "32050", "id": 180714, "director_name": "ZAKARIA BIN ABDUL HAMID"}, {"tarikh_anugerah": "1997-04-24", "nilai": "23780000", "tajuk": "Project Condo No.6 (200 Unit), Lot PT 52, Teluk Labuan Bilek, Mk. Sirusa, Port Dickson,           N. Sembilan.", "company": "MUHIBBAH ENGINEERING (M) BHD.", "cont_id": "32050", "id": 180715, "director_name": "ZAKARIA BIN ABDUL HAMID"}, {"tarikh_anugerah": "1997-05-20", "nilai": "9500000", "tajuk": "Proposed Ware House At Johor Port (Phase 1) For Cargonet Express\nSdn. Bhd.", "company": "MUHIBBAH ENGINEERING (M) BHD.", "cont_id": "32050", "id": 180716, "director_name": "ZAKARIA BIN ABDUL HAMID"}, {"tarikh_anugerah": "1997-06-18", "nilai": "85250000", "tajuk": "Cad. 3 B. 26 Tkt. Kondo. (426) 1 B. 5-8 Tkt. Ppuri. (34) 1 B. 9 Tkt. Ppuri (72) & 1 B.Perl. Tkt. Bgn. Lkereta. Phg.", "company": "MUHIBBAH ENGINEERING (M) BHD.", "cont_id": "32050", "id": 180717, "director_name": "ZAKARIA BIN ABDUL HAMID"}, {"tarikh_anugerah": "1997-06-18", "nilai": "10600000", "tajuk": "Design, Const. & Completion Of Single Storey Central Marketing Complex, Putrajaya\nPrecint, Kajang, Selangor.", "company": "MUHIBBAH ENGINEERING (M) BHD.", "cont_id": "32050", "id": 180718, "director_name": "ZAKARIA BIN ABDUL HAMID"}, {"tarikh_anugerah": "1997-10-17", "nilai": "0", "tajuk": "20 Tkt. & Blk. 'Annexe' Bank 7 Tkt. & 4 Tkt. B/Ment T.L.Kereta, Lot 28, Sek. 90, Jln. Tun Razak, Kuala Lumpur.", "company": "MUHIBBAH ENGINEERING (M) BHD.", "cont_id": "32050", "id": 180719, "director_name": "ZAKARIA BIN ABDUL HAMID"}, {"tarikh_anugerah": "1997-10-20", "nilai": "3393871", "tajuk": "Catamaran Berth At Tanjung Malai, Pulau Langkawi, Kedah.", "company": "MUHIBBAH ENGINEERING (M) BHD.", "cont_id": "32050", "id": 180720, "director_name": "ZAKARIA BIN ABDUL HAMID"}, {"tarikh_anugerah": "1997-10-21", "nilai": "2065892", "tajuk": "Catamaran Berth No.6, Deep Water Wharves At Butterworth, Penang.", "company": "MUHIBBAH ENGINEERING (M) BHD.", "cont_id": "32050", "id": 180721, "director_name": "ZAKARIA BIN ABDUL HAMID"}, {"tarikh_anugerah": "1997-11-03", "nilai": "1999366", "tajuk": "1 Blok Bgn. 2 Tkt. Kelab Rekreasi Marina Dll. Sbhg. Lot PT 2922, Tlk. Labuan Bilek, \nSi Rusa, Port Diskson, N.Sembilan.", "company": "MUHIBBAH ENGINEERING (M) BHD.", "cont_id": "32050", "id": 180722, "director_name": "ZAKARIA BIN ABDUL HAMID"}, {"tarikh_anugerah": "1997-12-08", "nilai": "299985880", "tajuk": "Pembangunan Pelabuhan Tjg. Pelepas, Johor Bahru, Johor.\n-  Wharf Structures", "company": "MUHIBBAH ENGINEERING (M) BHD.", "cont_id": "32050", "id": 180723, "director_name": "ZAKARIA BIN ABDUL HAMID"}, {"tarikh_anugerah": "1998-01-15", "nilai": "207869361", "tajuk": "Eng.,Prucurement, Const. & Commissioning Kertih Marine Facilities Expansion Project, Kertih, Terengganu.", "company": "MUHIBBAH ENGINEERING (M) BHD.", "cont_id": "32050", "id": 180724, "director_name": "ZAKARIA BIN ABDUL HAMID"}, {"tarikh_anugerah": "1998-01-23", "nilai": "39581990", "tajuk": "Turnkey Project Phase II A, Expansion Of North Butterworth Container Terminal, Pulau Pinang.", "company": "MUHIBBAH ENGINEERING (M) BHD.", "cont_id": "32050", "id": 180725, "director_name": "ZAKARIA BIN ABDUL HAMID"}, {"tarikh_anugerah": "1998-06-16", "nilai": "5880000", "tajuk": "Comp. & Comprehensive Design & Const.-MAS Visitors' Centre & Assoc. Buildings, Structure, & External Works, KLIA, Sepang", "company": "MUHIBBAH ENGINEERING (M) BHD.", "cont_id": "32050", "id": 180726, "director_name": "ZAKARIA BIN ABDUL HAMID"}, {"tarikh_anugerah": "1998-06-24", "nilai": "65000000", "tajuk": "Execution of the Remaining Works For Completion, Testing & Commissioning Of The MAS Catering Building AT KLIA, Sepang", "company": "MUHIBBAH ENGINEERING (M) BHD.", "cont_id": "32050", "id": 180727, "director_name": "ZAKARIA BIN ABDUL HAMID"}, {"tarikh_anugerah": "1998-12-14", "nilai": "4946965", "tajuk": "Proposed Extension to 100' Crane Beam On Wharf 9 & Assoc. Works At Klang Container Terminal, North Port, Port Klang", "company": "MUHIBBAH ENGINEERING (M) BHD.", "cont_id": "32050", "id": 180728, "director_name": "ZAKARIA BIN ABDUL HAMID"}, {"tarikh_anugerah": "1999-01-15", "nilai": "45600000", "tajuk": "C.F.O For  1,600 UnitS Of Low Cost On PTD 83406 & PTD 40167, Taman Desa Tebrau, Johor Bahru, Johor", "company": "MUHIBBAH ENGINEERING (M) BHD.", "cont_id": "32050", "id": 180729, "director_name": "ZAKARIA BIN ABDUL HAMID"}, {"tarikh_anugerah": "1999-06-30", "nilai": "45600000", "tajuk": "Rumah Pangsa Kos Rendah Di Atas PTD 40167 & 83406 Di Tmn. Desa Tebrau, Mukim Tebrau, Johor Bahru(WSN:", "company": "MUHIBBAH ENGINEERING (M) BHD.", "cont_id": "32050", "id": 180730, "director_name": "ZAKARIA BIN ABDUL HAMID"}, {"tarikh_anugerah": "1999-08-24", "nilai": "146710393", "tajuk": "Construction & Completion Of LNG 3 Berth At Bintulu Port, Bintulu, Sarawak.", "company": "MUHIBBAH ENGINEERING (M) BHD.", "cont_id": "32050", "id": 180731, "director_name": "ZAKARIA BIN ABDUL HAMID"}, {"tarikh_anugerah": "1999-11-13", "nilai": "67599645", "tajuk": "Const. & Com. Bridge BR9 At Putrajaya, Selangor - Contract No. : 1Ba/UT1/B09/CGEN/CON/10N/0428", "company": "MUHIBBAH ENGINEERING (M) BHD.", "cont_id": "32050", "id": 180732, "director_name": "ZAKARIA BIN ABDUL HAMID"}, {"tarikh_anugerah": "1999-11-22", "nilai": "74000000", "tajuk": "Const. & Comp. Of 600 Metres Container Wharf 3 At Westport, Pulau Indah, Port Klang, Selangor.", "company": "MUHIBBAH ENGINEERING (M) BHD.", "cont_id": "32050", "id": 180733, "director_name": "ZAKARIA BIN ABDUL HAMID"}, {"tarikh_anugerah": "1999-11-22", "nilai": "36982110", "tajuk": "Piling & Sub-Structure Works (Pakage 3B) - Prop. Univ. Tek. Petronas Dev., Bdr Seri Iskandar, Tronoh, Perak.", "company": "MUHIBBAH ENGINEERING (M) BHD.", "cont_id": "32050", "id": 180734, "director_name": "ZAKARIA BIN ABDUL HAMID"}, {"tarikh_anugerah": "2000-02-22", "nilai": "10000000", "tajuk": "Merekabentuk, Membina & Menyiapkan 100 Unit Kompleks Rumah Guru Mergong,", "company": "MUHIBBAH ENGINEERING (M) BHD.", "cont_id": "32050", "id": 180735, "director_name": "ZAKARIA BIN ABDUL HAMID"}, {"tarikh_anugerah": "2000-03-16", "nilai": "24980000", "tajuk": "Construction & Completion Of The Proposed Batang Igan Bridge And Access Roads In Sibu, Sarawak (Package 1A & 1B)", "company": "MUHIBBAH ENGINEERING (M) BHD.", "cont_id": "32050", "id": 180736, "director_name": "ZAKARIA BIN ABDUL HAMID"}, {"tarikh_anugerah": "2000-05-02", "nilai": "3800000", "tajuk": "Construction And Completion Of M&E; Works For Container Wharf 3 At Westport, Pulau Indah,", "company": "MUHIBBAH ENGINEERING (M) BHD.", "cont_id": "32050", "id": 180737, "director_name": "ZAKARIA BIN ABDUL HAMID"}, {"tarikh_anugerah": "2000-08-07", "nilai": "23827240", "tajuk": "Design Const & Comp Of Additional 100 Metres Wharf With Associated Wks North  Container Terminal", "company": "MUHIBBAH ENGINEERING (M) BHD.", "cont_id": "32050", "id": 180738, "director_name": "ZAKARIA BIN ABDUL HAMID"}, {"tarikh_anugerah": "2000-08-23", "nilai": "20000000", "tajuk": "I'structure Dev Distripark & Ass Installation  Adjacent - Container Freight Station (CFS)Area-Pelabuhan Tg Pelepas,Johor", "company": "MUHIBBAH ENGINEERING (M) BHD.", "cont_id": "32050", "id": 180739, "director_name": "ZAKARIA BIN ABDUL HAMID"}, {"tarikh_anugerah": "2000-10-30", "nilai": "1300000", "tajuk": "Proposed Renovation Of Terminal Building For Installation Of Escalator At Sultan Ismail Airport,", "company": "MUHIBBAH ENGINEERING (M) BHD.", "cont_id": "32050", "id": 180740, "director_name": "ZAKARIA BIN ABDUL HAMID"}, {"tarikh_anugerah": "2001-04-23", "nilai": "23052296", "tajuk": "Westport Dev - C & C Of Zone F & Quay Roadway (Pack. 1) At Container Terminal No. 3 (CT3), Westport P. Indah,", "company": "MUHIBBAH ENGINEERING (M) BHD.", "cont_id": "32050", "id": 180741, "director_name": "ZAKARIA BIN ABDUL HAMID"}, {"tarikh_anugerah": "2001-10-09", "nilai": "91609252", "tajuk": "Proposed Conversion Of Berths 12 & 13 Into Multi - Purpose Berths At North Port,", "company": "MUHIBBAH ENGINEERING (M) BHD.", "cont_id": "32050", "id": 180742, "director_name": "ZAKARIA BIN ABDUL HAMID"}, {"tarikh_anugerah": "2002-01-16", "nilai": "3225668", "tajuk": "Proposed Extension To 100' Crane Rail Beam On Wharf 8 & Associated Works At North Port", "company": "MUHIBBAH ENGINEERING (M) BHD.", "cont_id": "32050", "id": 180743, "director_name": "ZAKARIA BIN ABDUL HAMID"}, {"tarikh_anugerah": "2002-02-19", "nilai": "675305", "tajuk": "Repair & Reconstruction To Piles Of Mooring Dolphin No. 1 (MD-1), Adjoining Catwalks & Piers & Related Electrical Services At Berth LB3, Petrochemical Jetty, Westport, Pulau Indah", "company": "MUHIBBAH ENGINEERING (M) BHD.", "cont_id": "32050", "id": 180744, "director_name": "ZAKARIA BIN ABDUL HAMID"}, {"tarikh_anugerah": "2002-04-23", "nilai": "96500000", "tajuk": "Projek Pembangunan Pusat Hidrografi Negara, Pulau Indah Utk TLDM (Fasa 1)", "company": "MUHIBBAH ENGINEERING (M) BHD.", "cont_id": "32050", "id": 180745, "director_name": "ZAKARIA BIN ABDUL HAMID"}, {"tarikh_anugerah": "2002-05-13", "nilai": "586752", "tajuk": "Reconstruction Of Wharf Due To Vessel Impact Damage At Westport Container Wharf 12 Meter Mark 2800, Westport, Pulau Indah", "company": "MUHIBBAH ENGINEERING (M) BHD.", "cont_id": "32050", "id": 180746, "director_name": "ZAKARIA BIN ABDUL HAMID"}, {"tarikh_anugerah": "2002-05-17", "nilai": "11555500", "tajuk": "Construction & Completion Of 1 Unit Workshop, 2 Units RTG Workshop, 1 Unit CFS Building, 1 Unit Pump House, Water Tanks And Associated Wks At Container Terminal No. 3 (CT3), Westport Pulau Indah", "company": "MUHIBBAH ENGINEERING (M) BHD.", "cont_id": "32050", "id": 180747, "director_name": "ZAKARIA BIN ABDUL HAMID"}, {"tarikh_anugerah": "2002-12-18", "nilai": "3578348", "tajuk": "Proposed Outer Extension To LB3 Berth At Liquid Bulk Terminal, Westport, Pulau Indah, Port Klang", "company": "MUHIBBAH ENGINEERING (M) BHD.", "cont_id": "32050", "id": 180748, "director_name": "ZAKARIA BIN ABDUL HAMID"}, {"tarikh_anugerah": "2003-02-18", "nilai": "53862520", "tajuk": "Tender No: BPSB/19/2002 - Construction & Completion Of The Proposed Palm Oil Terminal At 2nd Inner Harbour, Bintulu Port", "company": "MUHIBBAH ENGINEERING (M) BHD.", "cont_id": "32050", "id": 180749, "director_name": "ZAKARIA BIN ABDUL HAMID"}, {"tarikh_anugerah": "2003-04-17", "nilai": "5609770", "tajuk": "Cadangan Kerja 'Dredging' Tasik Fasa 1B, Putrajaya", "company": "MUHIBBAH ENGINEERING (M) BHD.", "cont_id": "32050", "id": 180750, "director_name": "ZAKARIA BIN ABDUL HAMID"}, {"tarikh_anugerah": "2003-05-22", "nilai": "743035", "tajuk": "Mechanical And Electrical Works For Proposed Integrated Transport Information (It Is) For Refurbishment Of DBKL Tic, 1st Floor, Bangunan Dewan Bandaraya Kuala Lumpur, Jalan Raja Laut", "company": "MUHIBBAH ENGINEERING (M) BHD.", "cont_id": "32050", "id": 180751, "director_name": "ZAKARIA BIN ABDUL HAMID"}, {"tarikh_anugerah": "2003-08-01", "nilai": "1350000", "tajuk": "Const. & Comple. Of Reinstatement Works To Grid 137 - 138 (Meter Mark 115 - 121) At Westport, Pulau Indah, Port Klang", "company": "MUHIBBAH ENGINEERING (M) BHD.", "cont_id": "32050", "id": 180752, "director_name": "ZAKARIA BIN ABDUL HAMID"}, {"tarikh_anugerah": "2003-08-25", "nilai": "3900000", "tajuk": "Construction & Completion Of Extension Quay No. 2 & 3, TS/TSD/007-2003 (APPR.NO.TSD/005/2003)", "company": "MUHIBBAH ENGINEERING (M) BHD.", "cont_id": "32050", "id": 180753, "director_name": "ZAKARIA BIN ABDUL HAMID"}, {"tarikh_anugerah": "2003-09-17", "nilai": "21000000", "tajuk": "Proposed Const. & Comple. Of Toll Plazas, Administration Building, Supervision Buildings & Other Ancillary Buildings At Guthrie Corridor Expressway", "company": "MUHIBBAH ENGINEERING (M) BHD.", "cont_id": "32050", "id": 180754, "director_name": "ZAKARIA BIN ABDUL HAMID"}, {"tarikh_anugerah": "2004-02-11", "nilai": "38888000", "tajuk": "Proposed Design & Build For The Conversion Of Berth 14 Into A Multi-Purpose Berth & Associated Works At Northport, Port Klang", "company": "MUHIBBAH ENGINEERING (M) BHD.", "cont_id": "32050", "id": 180755, "director_name": "ZAKARIA BIN ABDUL HAMID"}, {"tarikh_anugerah": "2004-03-30", "nilai": "24950000", "tajuk": "Package 2 Jetty Works For Independent Oil Terminal Project Senari, Kuching", "company": "MUHIBBAH ENGINEERING (M) BHD.", "cont_id": "32050", "id": 180756, "director_name": "ZAKARIA BIN ABDUL HAMID"}, {"tarikh_anugerah": "2004-06-15", "nilai": "107680076", "tajuk": "Westport Development - Const & Comp Of CT4 & CT5 Wharves & Access Bridges At Westport Container Terminal, Pulau Indah (WP/KMT-TSD/2004-02/04)", "company": "MUHIBBAH ENGINEERING (M) BHD.", "cont_id": "32050", "id": 180757, "director_name": "ZAKARIA BIN ABDUL HAMID"}, {"tarikh_anugerah": "2004-10-30", "nilai": "9247600", "tajuk": "Design, Construction, Delivery, Testing & Commissioning Of 1 Unit Bulk Cargo Level Luffing Crane For Bulk Terminal, Jalan Pelabuhan, Pelabuhan Utara", "company": "MUHIBBAH ENGINEERING (M) BHD.", "cont_id": "32050", "id": 180758, "director_name": "ZAKARIA BIN ABDUL HAMID"}, {"tarikh_anugerah": "2005-07-30", "nilai": "123919707", "tajuk": "Proposed Design, Construction & Completion Of 914 Units Of Government Apartment At Parcel 5R4 In Precint 5, Putrajaya", "company": "MUHIBBAH ENGINEERING (M) BHD.", "cont_id": "32050", "id": 180759, "director_name": "ZAKARIA BIN ABDUL HAMID"}, {"tarikh_anugerah": "2006-04-14", "nilai": "3450000", "tajuk": "Repair Of Superstructure With Associated Works At Star Cruises Jetty,Pulau Langkawi", "company": "MUHIBBAH ENGINEERING (M) BHD.", "cont_id": "32050", "id": 180760, "director_name": "ZAKARIA BIN ABDUL HAMID"}, {"tarikh_anugerah": "2006-09-22", "nilai": "8366450", "tajuk": "Design-Build Services For The Perimeter Security Upgrade Project At American Embassy Kuala Lumpur, 376 Jalan Tun Razak", "company": "MUHIBBAH ENGINEERING (M) BHD.", "cont_id": "32050", "id": 180761, "director_name": "ZAKARIA BIN ABDUL HAMID"}, {"tarikh_anugerah": "2007-01-23", "nilai": "2336000", "tajuk": "Pembinaan Jambatan Jeti Pusat Hidrografi Nasional ( PHN ), Klang", "company": "MUHIBBAH ENGINEERING (M) BHD.", "cont_id": "32050", "id": 180762, "director_name": "ZAKARIA BIN ABDUL HAMID"}, {"tarikh_anugerah": "2007-07-06", "nilai": "1100000000", "tajuk": "Privatization Of The South Klang Valley Expressway", "company": "MUHIBBAH ENGINEERING (M) BHD.", "cont_id": "32050", "id": 180763, "director_name": "ZAKARIA BIN ABDUL HAMID"}, {"tarikh_anugerah": "2007-11-13", "nilai": "1675000", "tajuk": "Proposed Accident Repair Works At Cement Jetty Westports Pulau Indah Due To Collision Involving TSDH Inai Anggerik On 21 September 2007", "company": "MUHIBBAH ENGINEERING (M) BHD.", "cont_id": "32050", "id": 180764, "director_name": "ZAKARIA BIN ABDUL HAMID"}, {"tarikh_anugerah": "2008-03-31", "nilai": "7968315", "tajuk": "Cad.Membina Sebuah Hotel Butik 3 Tingkat Mengandungi 56 Bilik Dan Sebuah Pangsapuri 4 Tingkat Mengandungi 32 Unit Di Atas Plot B2 Milik Casa Del Rio (M) Sdn.Bhd. - Earthworks, Piling & Pile Cap Works", "company": "MUHIBBAH ENGINEERING (M) BHD.", "cont_id": "32050", "id": 180765, "director_name": "ZAKARIA BIN ABDUL HAMID"}, {"tarikh_anugerah": "2008-04-15", "nilai": "80333000", "tajuk": "Proposed Redevelopment For Deepwater Facilities At Quay 6 (MMHE)", "company": "MUHIBBAH ENGINEERING (M) BHD.", "cont_id": "32050", "id": 180766, "director_name": "ZAKARIA BIN ABDUL HAMID"}, {"tarikh_anugerah": "2009-02-25", "nilai": "109216922", "tajuk": "Engineering, Procurement, Construction And Commissioning Of The Central Oil Distrubution Terminal At Tg Manis,", "company": "MUHIBBAH ENGINEERING (M) BHD.", "cont_id": "32050", "id": 180767, "director_name": "ZAKARIA BIN ABDUL HAMID"}, {"tarikh_anugerah": "2010-10-13", "nilai": "205795032", "tajuk": "The Prop Design, Const & Comp Of Government Office Building & External Work At Lot 4G5, Precinct 4 At The Federal Government Adminstrative Centre, Putrajaya", "company": "MUHIBBAH ENGINEERING (M) BHD.", "cont_id": "32050", "id": 180768, "director_name": "ZAKARIA BIN ABDUL HAMID"}, {"tarikh_anugerah": "2011-02-28", "nilai": "8500000", "tajuk": "The C & C Of New Dolpins Wth Additional Deck Area And Ancillary Wrks Fr Port Klang Cruise Centre Sdn Bhd Located At Glenn Cruise Terminal , Pulau Indah, Port Klang Cruise Centre, Pelabuhan Klang", "company": "MUHIBBAH ENGINEERING (M) BHD.", "cont_id": "32050", "id": 180769, "director_name": "ZAKARIA BIN ABDUL HAMID"}, {"tarikh_anugerah": "2011-06-23", "nilai": "338406914", "tajuk": "Proposed Development Of A Multipurpose Wharf & Associated Facilities At Container Terminal 4 (CT4) As An Extention To Existing Wharf 8 & Upgrading Of Wharf 16", "company": "MUHIBBAH ENGINEERING (M) BHD.", "cont_id": "32050", "id": 180770, "director_name": "ZAKARIA BIN ABDUL HAMID"}], "founding_date": null, "name": "Zakaria Bin Abdul Hamid", "url": "http://sinar-malaysia.popit.mysociety.org/api/v0.1/persons/545e483f5222837c2c059623", "gender": null, "slug": "zakaria-bin-abdul-hamid", "death_date": null, "proxy_image": null, "start_date": null, "memberships": [{"area_id": null, "end_date": null, "url": "http://sinar-malaysia.popit.mysociety.org/api/v0.1/memberships/545e62d45222837c2c05b092", "area_name": null, "html_url": "http://sinar-malaysia.popit.mysociety.org/memberships/545e62d45222837c2c05b092", "id": 1965, "label": null, "organization_id": "545de8665222837c2c0586c0", "post_id": "545e4d5b5222837c2c05988b", "membership_id": "545e62d45222837c2c05b092", "role": "Parliamentary Candidate", "person_id": 3590, "director_name": "Zakaria Bin Abdul Hamid", "start_date": "2013"}, {"area_id": null, "end_date": null, "url": "http://sinar-malaysia.popit.mysociety.org/api/v0.1/memberships/545f822c5222837c2c05b93f", "area_name": null, "html_url": "http://sinar-malaysia.popit.mysociety.org/memberships/545f822c5222837c2c05b93f", "id": 3591, "label": null, "organization_id": "545e01f75222837c2c058703", "post_id": "545f7f865222837c2c05b8f3", "membership_id": "545f822c5222837c2c05b93f", "role": "Member of State Assembly", "person_id": 3590, "director_name": "Zakaria Bin Abdul Hamid", "start_date": "2013"}], "birth_date": null, "num_projects": 64, "email": null, "initials": null}